{
  "telegram": {
    "bot_token": "REPLACE_ME"
  },
  "routing": {
    "user_email_map": {
      "TelegramID": "email for Kindle"
    }
  },
  "smtp": {
    "host": "smtp.gmail.com",
    "port": 587,
    "username": "your_mail@gmail.com",
    "password": "your_app_password",
    "from_email": "your_mail@gmail.com",
    "use_tls": true
  },
  "otp_notify_chat_id": "123456",
  "max_email_bytes": 15728640,
  "ru_only_search": true,
  "inpx_name": "/path/to/flibusta_fb2_local.inpx",
  "work_dir": "/path/to/flibusta/runtime"
}
